qdrant_vsql/__init__.py
qdrant_vsql/_version.py
qdrant_vsql/filtering.py
qdrant_vsql-0.1.2.dist-info/licenses/LICENSE
qdrant_vsql-0.1.2.dist-info/METADATA
qdrant_vsql-0.1.2.dist-info/WHEEL
qdrant_vsql-0.1.2.dist-info/top_level.txt
qdrant_vsql-0.1.2.dist-info/RECORD
