Metadata-Version: 2.4
Name: qdrant-vsql
Version: 0.1.2
Summary: Bringing some SQL to Qdrant
Author-email: Raul Carlomagno <rcarlomagno@gmail.com>
License-Expression: MIT
Project-URL: Homepage, https://github.com/raulcarlomagno/qdrant_vsql
Project-URL: Repository, https://github.com/raulcarlomagno/qdrant_vsql
Project-URL: Issues, https://github.com/raulcarlomagno/qdrant_vsql/issues
Keywords: qdrant,vector,search,sql
Classifier: Programming Language :: Python :: 3
Classifier: Operating System :: OS Independent
Requires-Python: >=3.9
License-File: LICENSE
Requires-Dist: parsimonious<1.0,>=0.10.0
Requires-Dist: qdrant-client<2.0,>=1.14.2
Provides-Extra: dev
Requires-Dist: pytest>=8.0; extra == "dev"
Requires-Dist: ruff>=0.11.0; extra == "dev"
Dynamic: license-file
